{
  "issue_id": "this-is-not-the-power-law-n-0-062-predic",
  "finding_slug": "zaremba-A12-logarithmic-convergence",
  "found_by_reviews": [
    "zaremba-A12-logarithmic-convergence_o3pro-review",
    "zaremba-A12-logarithmic-convergence_peer-review"
  ],
  "severity": "minor",
  "description": "Text is revised to clearly state that Bourgain-Kontorovich's 2\u03b4\u22121 exponent controls the growth of R(d)\u2014the count of d representable as n/d\u2014but does not provide an effective or quantitative rate for density convergence itself. States explicitly that BK proves density 1 non-effectively, and 'logarithmic' behavior observed here is not theoretically predicted by BK.",
  "status": "resolved",
  "action_taken": "Text is revised to clearly state that Bourgain-Kontorovich's 2\u03b4\u22121 exponent controls the growth of R(d)\u2014the count of d representable as n/d\u2014but does not provide an effective or quantitative rate for density convergence itself. States explicitly that BK proves density 1 non-effectively, and 'logarithmic' behavior observed here is not theoretically predicted by BK.",
  "resolved_at": "2026-04-07T00:11:38.901967+00:00",
  "commits": [
    "e37fcff"
  ]
}